bigbucket/__init__.py
bigbucket/client.py
bigbucket/errors.py
bigbucket/utils.py
bigbucket/version.py
bigbucket-0.5.0.dist-info/LICENSE
bigbucket-0.5.0.dist-info/METADATA
bigbucket-0.5.0.dist-info/WHEEL
bigbucket-0.5.0.dist-info/top_level.txt
bigbucket-0.5.0.dist-info/RECORD
