Metadata-Version: 2.1
Name: bigbucket
Version: 0.5.0
Summary: Python3 client for Bigbucket
Home-page: https://github.com/adrianchifor/bigbucket-python
Author: Adrian Chifor
Author-email: me@adrianchifor.com
License: GNU General Public License v3 (GPLv3)
Keywords: serverless cloud bigtable database gcs storage client
Platform: UNKNOWN
Classifier: Development Status :: 4 - Beta
Classifier: Intended Audience :: Developers
Classifier: Topic :: Software Development :: Libraries :: Python Modules
Classifier: Topic :: System :: Distributed Computing
Classifier: Topic :: Database
Classifier: License :: OSI Approved :: GNU General Public License v3 (GPLv3)
Classifier: Programming Language :: Python :: 3.6
Classifier: Programming Language :: Python :: 3.7
Requires-Python: >=3.6
Requires-Dist: requests-gcp
